pyIntensityFeatures/__init__.py
pyIntensityFeatures/_main.py
pyIntensityFeatures/instruments/__init__.py
pyIntensityFeatures/instruments/satellites.py
pyIntensityFeatures/proc/__init__.py
pyIntensityFeatures/proc/boundaries.py
pyIntensityFeatures/proc/fitting.py
pyIntensityFeatures/proc/intensity.py
pyIntensityFeatures/tests/__init__.py
pyIntensityFeatures/tests/test_instruments_satellites.py
pyIntensityFeatures/tests/test_main.py
pyIntensityFeatures/tests/test_proc_boundaries.py
pyIntensityFeatures/tests/test_proc_fitting.py
pyIntensityFeatures/tests/test_proc_intensity.py
pyIntensityFeatures/tests/test_utils_checks.py
pyIntensityFeatures/tests/test_utils_coords.py
pyIntensityFeatures/tests/test_utils_distributions.py
pyIntensityFeatures/tests/test_utils_grids.py
pyIntensityFeatures/tests/test_utils_output.py
pyIntensityFeatures/utils/__init__.py
pyIntensityFeatures/utils/checks.py
pyIntensityFeatures/utils/coords.py
pyIntensityFeatures/utils/distributions.py
pyIntensityFeatures/utils/grids.py
pyIntensityFeatures/utils/output.py
pyintensityfeatures-0.1.0.dist-info/licenses/LICENSE
pyintensityfeatures-0.1.0.dist-info/METADATA
pyintensityfeatures-0.1.0.dist-info/WHEEL
pyintensityfeatures-0.1.0.dist-info/top_level.txt
pyintensityfeatures-0.1.0.dist-info/RECORD
