Metadata-Version: 2.4
Name: pyIntensityFeatures
Version: 0.1.0
Summary: Identify features, such as auroral luminosity boundaries, in imager data
Home-page: https://github.com/aburrell/pyIntensityFeatures
Author-email: Angeline Burrell <angeline.g.burrell.civ@us.navy.mil>
License: Copyright (c) 2025, Angeline G. Burrell (AGB), Gareth Chisham (GC), and
Project-URL: Documentation, https://pyintensityfeatures.readthedocs.io/en/latest/
Project-URL: Source, https://github.com/aburrell/pyIntensityFeatures
Project-URL: Tracker, https://github.com/aburrell/pyIntensityFeatures/issues
Project-URL: Download, https://github.com/aburrell/pyIntensityFeatures/releases
Keywords: aurora,aurora australis,aurora borealis,boundaries,imager,ionosphere,heliophysics,magnetosphere,northern lights,southern lights,features,intensity
Classifier: Development Status :: 3 - Alpha
Classifier: Topic :: Scientific/Engineering :: Physics
Classifier: Topic :: Scientific/Engineering :: Atmospheric Science
Classifier: Intended Audience :: Science/Research
Classifier: License :: OSI Approved :: BSD License
Classifier: Natural Language :: English
Classifier: Programming Language :: Python :: 3
Classifier: Programming Language :: Python :: 3.10
Classifier: Programming Language :: Python :: 3.11
Classifier: Programming Language :: Python :: 3.12
Classifier: Programming Language :: Python :: 3.13
Classifier: Operating System :: POSIX :: Linux
Classifier: Operating System :: MacOS :: MacOS X
Classifier: Operating System :: Microsoft :: Windows
Requires-Python: >=3.9
License-File: LICENSE
Requires-Dist: aacgmv2
Requires-Dist: numpy
Requires-Dist: pandas
Requires-Dist: scipy
Requires-Dist: xarray
Provides-Extra: apex
Requires-Dist: apexpy; extra == "apex"
Provides-Extra: test
Requires-Dist: coverage[toml]; extra == "test"
Requires-Dist: flake8; extra == "test"
Requires-Dist: flake8-docstrings; extra == "test"
Provides-Extra: doc
Requires-Dist: myst_parser; extra == "doc"
Requires-Dist: numpydoc; extra == "doc"
Requires-Dist: pyproject-parser; extra == "doc"
Requires-Dist: sphinx; extra == "doc"
Requires-Dist: sphinx-autoapi; extra == "doc"
Requires-Dist: sphinx_rtd_theme; extra == "doc"
Dynamic: license-file
